{
    "debug_info": true,
    "debug_time_s":5,

    "pc_topic": "/cloud_map",
    "cmd_vel_topic": "/cmd_vel",
    "tf_topic":"/tf",
    "height":1,

    "map_resolution":0.1,
    "local_map_size":5,
    "global_map_size":200,
    "map_unknown_transparency":false,
    "map_low_resolution_division_factor":4,

    "ransac_iterations":100,

    "roughness_frame_id":"map",
    "roughness_topic_global": "/roughness_costmap",
    "roughness_topic_local": "/roughness_costmap_local",
    "roughness_threshold": 0.2,
    "roughness_shift":0.003,


    "imu_topic": "/imu/data_raw",
    "imu_sampling_frequency":200,
    "imu_filter_frequency":27.5,
    "imu_filter_bandwidth":5.0,

    "w_k":1.0,
    "alpha_0":0.1,
    "lambda_decay":0.02,
    "beta":0.9,
    "error_moving_avg":0.0
}